src/libreria.v
`timescale 1ns/1ps

`include "./src/definiciones.v"

// -----------------------------------------------
// Modulos de compuertas
// -----------------------------------------------
// Cada compuerta debe tener la siguiente línea :
//   always @(posedge salida)
//     BancoPruebas.trans.PwrCntr[PwrC] = BancoPruebas.trans.PwrCntr[PwrC] + `Px;
// Donde se guardan las transiciones de 0 a 1 que ocurren en cada módulo
// Recordar que el consumo de potencia se da en las transiciones de la salida.
// 'Px = Tabla de ponderaciones de potencia

// Defina cada compuerta utilizando de ejemplo el modulo inversor, el programa
// no será ejecutado hasta que todas las compuertas sean definidas correctamente.


// -----------------------------------------------
// Inversor a = ~b;
// -----------------------------------------------

module inv_p(a, b);
  parameter
    PwrC = 0;

  input b;
  output a;

  assign #`d_inv a = ~b;

  //En las transiciones de 0 a 1 en las salidas se consume energia
  always @(posedge a)
    BancoPruebas.mem_trans.PwrCntr[PwrC] = BancoPruebas.mem_trans.PwrCntr[PwrC] + `Pinv;
endmodule



//*************************************************************************
//Compuerta and de 2 entradas

module and2_p(a, b, c);
  parameter
    PwrC = 0;

  input b, c;
  output a;

  assign #`d_and2 a = &{b,c};

  //En las transiciones de 0 a 1 en las salidas se consume energia
  always @(posedge a)
    BancoPruebas.mem_trans.PwrCntr[PwrC] = BancoPruebas.mem_trans.PwrCntr[PwrC] + `Pand2;
endmodule

//*************************************************************************
//Compuerta and de 3 entradas

module and3_p(a, b, c, d);
  parameter
    PwrC = 0;

  input b, c, d;
  output a;

  assign #`d_and3 a = &{b,c,d};

  //En las transiciones de 0 a 1 en las salidas se consume energia
  always @(posedge a)
    BancoPruebas.mem_trans.PwrCntr[PwrC] = BancoPruebas.mem_trans.PwrCntr[PwrC] + `Pand3;

endmodule

//*************************************************************************
//Compuerta and de 4 entradas

module and4_p(a, b, c, d, e);
  parameter
    PwrC = 0;

  input b, c, d, e;
  output a;

  assign #`d_and4 a = &{b,c,d,e};

  //En las transiciones de 0 a 1 en las salidas se consume energia
  always @(posedge a)
    BancoPruebas.mem_trans.PwrCntr[PwrC] = BancoPruebas.mem_trans.PwrCntr[PwrC] + `Pand4;

endmodule

//*************************************************************************
//Compuerta and de 5 entradas

module and5_p(a, b, c, d, e, f);
  parameter
    PwrC = 0;

  input b, c, d, e, f;
  output a;

  assign #`d_and5 a = &{b,c,d,e,f};

  //En las transiciones de 0 a 1 en las salidas se consume energia
  always @(posedge a)
    BancoPruebas.mem_trans.PwrCntr[PwrC] = BancoPruebas.mem_trans.PwrCntr[PwrC] + `Pand5;

endmodule

//*************************************************************************
//Compuerta or de 2 entradas

module or2_p(a, b, c);
  parameter
    PwrC = 0;

  input b, c;
  output a;

  assign #`d_or2 a = |{b,c};

  //En las transiciones de 0 a 1 en las salidas se consume energia
  always @(posedge a)
    BancoPruebas.mem_trans.PwrCntr[PwrC] = BancoPruebas.mem_trans.PwrCntr[PwrC] + `Por2;
endmodule

//*************************************************************************
//Compuerta or de 3 entradas

module or3_p(a, b, c, d);
  parameter
    PwrC = 0;

  input b, c, d;
  output a;

  assign #`d_or3 a = |{b,c,d};

  //En las transiciones de 0 a 1 en las salidas se consume energia
  always @(posedge a)
    BancoPruebas.mem_trans.PwrCntr[PwrC] = BancoPruebas.mem_trans.PwrCntr[PwrC] + `Por3;
endmodule


//*************************************************************************
//Compuerta or de 4 entradas

module or4_p(a, b, c, d, e);
  parameter
    PwrC = 0;

  input b, c, d, e;
  output a;

  assign #`d_or4 a = |{b,c,d,e};

  //En las transiciones de 0 a 1 en las salidas se consume energia
  always @(posedge a)
    BancoPruebas.mem_trans.PwrCntr[PwrC] = BancoPruebas.mem_trans.PwrCntr[PwrC] + `Por4;
endmodule


//*************************************************************************
//Compuerta or de 5 entradas

module or5_p(a, b, c, d, e, f);
  parameter
    PwrC = 0;

  input b, c, d, e, f;
  output a;

  assign #`d_or5 a = |{b,c,d,e,f};

  //En las transiciones de 0 a 1 en las salidas se consume energia
  always @(posedge a)
    BancoPruebas.mem_trans.PwrCntr[PwrC] = BancoPruebas.mem_trans.PwrCntr[PwrC] + `Por5;
endmodule

//*************************************************************************
//Compuerta xor de 2 entradas

module xor2_p(a, b, c);
  parameter
    PwrC = 0;

  input b, c;
  output a;

  assign #`d_xor2 a = ^{b,c};

  //En las transiciones de 0 a 1 en las salidas se consume energia
  always @(posedge a)
    BancoPruebas.mem_trans.PwrCntr[PwrC] = BancoPruebas.mem_trans.PwrCntr[PwrC] + `Pxor2;
endmodule

//*************************************************************************
//Compuerta xor de 3 entradas

module xor3_p(a, b, c, d);
  parameter
    PwrC = 0;

  input b, c, d;
  output a;

  assign #`d_xor3 a = ^{b,c,d};

  //En las transiciones de 0 a 1 en las salidas se consume energia
  always @(posedge a)
    BancoPruebas.mem_trans.PwrCntr[PwrC] = BancoPruebas.mem_trans.PwrCntr[PwrC] + `Pxor3;
endmodule

src/sumador_rizado.v
// -----------------------------------------------
// Sumador completo de un bit
// -----------------------------------------------
// Entradas: A, B, Cin
// Salida Cout y S
`timescale 1ns/1ps

module sumador_completo (a, b, ci, s, co);      // see complete adder diagram on docs
  parameter
    PwrC = 0;
  input wire a,b,ci;
  output reg s,co;
  wire s1,s2,s3,s4,s5,s6;

  xor2_p xor1(
    //INPUTS
    .c     (a),
    .b     (b),
    // OUTPUTS
    .a     ( s1)
  );

    xor2_p xor2(
    //INPUTS
    .c     (s1),
    .b     (ci),
    // OUTPUTS
    .a     (s2)
  );


// carry logic

  and2_p and1(
    //INPUTS
    .c     (ci),
    .b     (a),
    // OUTPUTS
    .a     ( s3)
  );

    and2_p and2(
    //INPUTS
    .c     (ci),
    .b     (b),
    // OUTPUTS
    .a     ( s4)
  );

    and2_p and3(
    //INPUTS
    .c     (a),
    .b     (b),
    // OUTPUTS
    .a     ( s5)
  );


   or3_p or1(
    //INPUTS
    .b     (s3),
    .c     (s4),
    .d     (s5),
    // OUTPUTS
    .a     ( s6)
  );


  always@(*) begin
    s = s2;
    co = s6;
  end

endmodule


// -----------------------------------------------
// Sumador rizado de 8 bits
// -----------------------------------------------
// this module can be implemented more quickly with a generate block.

module SUM_RIZADO(a, b, ci, s, co);
  parameter
    PwrC = 0;
  input wire [7:0] a,b;
  input wire ci;
  output reg [7:0] s;
  output reg co;
  wire [7:0] carry, sn; //c0,c1,c2,c3,c4,c5,c6,c7,s0,s1,s2,s3,s4,s5,s6,s7;

  sumador_completo sum0(
    //inputs
    .a      (a[0]),
    .b      (b[0]),
    .ci     (ci),
    //outputs
    .s      (sn[0]),
    .co     (carry[0])
  );

  sumador_completo sum1(
    //inputs
    .a      (a[1]),
    .b      (b[1]),
    .ci     (carry[0]),
    //outputs
    .s      (sn[1]),
    .co     (carry[1])
  );

  sumador_completo sum2(
    //inputs
    .a      (a[2]),
    .b      (b[2]),
    .ci     (carry[1]),
    //outputs
    .s      (   sn[2]),
    .co     (carry[2])
  );

  sumador_completo sum3(
    //inputs
    .a      (a[3]),
    .b      (b[3]),
    .ci     (carry[2]),
    //outputs
    .s      (   sn[3]),
    .co     (carry[3])
  );

  sumador_completo sum4(
    //inputs
    .a      (a[4]),
    .b      (b[4]),
    .ci     (carry[3]),
    //outputs
    .s      (   sn[4]),
    .co     (carry[4])
  );

  sumador_completo sum5(
    //inputs
    .a      (a[5]),
    .b      (b[5]),
    .ci     (carry[4]),
    //outputs
    .s      (   sn[5]),
    .co     (carry[5])
  );

  sumador_completo sum6(
    //inputs
    .a      (a[6]),
    .b      (b[6]),
    .ci     (carry[5]),
    //outputs
    .s      (   sn[6]),
    .co     (carry[6])
  );

  sumador_completo sum7(
    //inputs
    .a      (a[7]),
    .b      (b[7]),
    .ci     (carry[6]),
    //outputs
    .s      (   sn[7]),
    .co     (carry[7])
  );

  always@(*) begin
    s = sn[7:0];
    co = carry[7];
  end

endmodule

testbenches/banco_pruebas.v
`timescale 1ns/1ps

`include "./src/libreria.v"
//`include "./src/sumador_logico.v"
`include "./src/sumador_rizado.v"
//`include "./src/sumador_look.v"

// -----------------------------------------------
// Contadores de transiciónes
// -----------------------------------------------
// NumPwrCntr debe tener el numero de contadores N, menos uno: NumPwrCntr = N - 1
// Ndir debe ser tal que (2^(Ndir+1) - 1) > NumPwrCntr.
// Nota: Si no se cumple las condiciones se genera un loop infinito.
`define NumPwrCntr 2
`define Ndir 1


// -----------------------------------------------
// Modulo: Contador de transicion
// -----------------------------------------------

module contador_Transicion (dir, LE, dato);
  input [`Ndir:0] dir;
  input LE;
  inout [31:0] dato;
  reg [31:0] PwrCntr [`NumPwrCntr:0];

  //Control de E/S del puerto de datos
  assign dato = (LE)? PwrCntr[dir] : 32'bz;

  //Ciclo de escritura para la memoria
  always @(dir or negedge LE or dato)
    begin
      if (~LE) //escritura
        PwrCntr[dir] = dato;
    end
endmodule



// -----------------------------------------------
// Banco de pruebas
// -----------------------------------------------

module BancoPruebas;
  reg [7:0] oprA, oprB;
  reg [31:0] Contador;
  reg [`Ndir:0] dir;
  reg LE;
  integer semilla,Contador_sumas, valor;
  wire [31:0] dato;
  wire [7:0] Suma, Suma_logico, Suma_look;
  wire carry_rizado, carry_logico, carry_look;

  //Conexion a la memoria de contadores de transicion
  contador_Transicion mem_trans (dir, LE, dato);
  //Control de E/S del puerto de dato de la memoria de contadores
  assign dato = (~LE)? Contador : 32'bz;

  // ---------------------------------------------------------------
  // Nota:
  // Sumador de rizado usa contador 0 de la memoria
  // Sumador de logico usa contador 1 de la memoria
  // Sumador lookahead usa contador 2 de la memoria
  // ---------------------------------------------------------------

  SUM_RIZADO sumadorRizado (oprA, oprB, 1'b0, Suma, carry_rizado);                    // Instancia de sumador de rizado
  //SUM8_LOGICO #(1)  sumadorLogico (oprA, oprB, 1'b0, Suma_logico, carry_logico);          // Instancia de sumador logico
  //SUM8_LOOKAHEAD #(2) sumadorLookahead (oprA, oprB, 1'b0, Suma_look, carry_look);         // Instancia de sumador look ahead

  initial
    begin
      $dumpfile ("Sumadores.vcd");
      $dumpvars;

      // Borrar memoria de transiciones
      #1 LE = 0;
      Contador = 0;
      Contador_sumas = 0;

      for (dir=0; dir<=`NumPwrCntr; dir=dir+1)
        #1 Contador = 0;

      // ------------------------------------------------------
      // Semilla inicial para el generador de numeros aleatorios
      // ------------------------------------------------------

      semilla = 10;

      #50
      // Cada llamada de una suma se va a variar el contador de sumas
      Contador_sumas = Contador_sumas + 1;
      //Primer par de operandos para los sumadores
      oprA = $random(semilla);
      oprB = $random(semilla);

      // Código ciclico por el número de sumas deseadas.
      repeat (99)
        begin
          #50
	         $display ("No. Suma = %d: Operador A = %d, Operador B = %d, Sumador_1 = %d, Sumador_2 = %d, Sumador_3=%d",Contador_sumas,oprA,oprB,Suma,Suma_logico,Suma_look);
	          Contador_sumas = Contador_sumas + 1;
            oprB = $random(semilla);
            oprA = $random(semilla);
        end

      #50 $display ("No. Suma = %d: Operador A = %d, Operador B = %d, Sumador_1 = %d, Sumador_2 = %d, Sumador_3=%d",Contador_sumas,oprA,oprB,Suma,Suma_logico,Suma_look);
      //Lea y despliegue la memoria con contadores de transicion
      $display ("Semilla: ", semilla);
      #50 LE = 1;

      for (dir=0; dir<=`NumPwrCntr; dir=dir+1)
        begin
          #1 Contador = dato;
          $display(,,"PwrCntr[%d]: %d", dir, Contador);
        end
      #1 $finish;
    end

endmodule

Sumadores.vcd
$date
	Sat Oct 31 18:29:45 2020
$end
$version
	Icarus Verilog
$end
$timescale
	1ps
$end
$scope module BancoPruebas $end
$var wire 8 ! Suma_logico [7:0] $end
$var wire 8 " Suma_look [7:0] $end
$var wire 32 # dato [31:0] $end
$var wire 1 $ carry_rizado $end
$var wire 8 % Suma [7:0] $end
$var reg 32 & Contador [31:0] $end
$var reg 1 ' LE $end
$var reg 2 ( dir [1:0] $end
$var reg 8 ) oprA [7:0] $end
$var reg 8 * oprB [7:0] $end
$var integer 32 + Contador_sumas [31:0] $end
$var integer 32 , semilla [31:0] $end
$scope module mem_trans $end
$var wire 1 ' LE $end
$var wire 32 - dato [31:0] $end
$var wire 2 . dir [1:0] $end
$upscope $end
$scope module sumadorRizado $end
$var wire 8 / a [7:0] $end
$var wire 8 0 b [7:0] $end
$var wire 1 1 ci $end
$var wire 8 2 sn [7:0] $end
$var wire 8 3 carry [7:0] $end
$var reg 1 $ co $end
$var reg 8 4 s [7:0] $end
$scope module sum0 $end
$var wire 1 5 a $end
$var wire 1 6 b $end
$var wire 1 1 ci $end
$var wire 1 7 s6 $end
$var wire 1 8 s5 $end
$var wire 1 9 s4 $end
$var wire 1 : s3 $end
$var wire 1 ; s2 $end
$var wire 1 < s1 $end
$var reg 1 = co $end
$var reg 1 > s $end
$scope module and1 $end
$var wire 1 5 b $end
$var wire 1 1 c $end
$var wire 1 : a $end
$upscope $end
$scope module and2 $end
$var wire 1 6 b $end
$var wire 1 1 c $end
$var wire 1 9 a $end
$upscope $end
$scope module and3 $end
$var wire 1 6 b $end
$var wire 1 5 c $end
$var wire 1 8 a $end
$upscope $end
$scope module or1 $end
$var wire 1 : b $end
$var wire 1 9 c $end
$var wire 1 8 d $end
$var wire 1 7 a $end
$upscope $end
$scope module xor1 $end
$var wire 1 6 b $end
$var wire 1 5 c $end
$var wire 1 < a $end
$upscope $end
$scope module xor2 $end
$var wire 1 1 b $end
$var wire 1 < c $end
$var wire 1 ; a $end
$upscope $end
$upscope $end
$scope module sum1 $end
$var wire 1 ? a $end
$var wire 1 @ b $end
$var wire 1 A ci $end
$var wire 1 B s6 $end
$var wire 1 C s5 $end
$var wire 1 D s4 $end
$var wire 1 E s3 $end
$var wire 1 F s2 $end
$var wire 1 G s1 $end
$var reg 1 H co $end
$var reg 1 I s $end
$scope module and1 $end
$var wire 1 ? b $end
$var wire 1 A c $end
$var wire 1 E a $end
$upscope $end
$scope module and2 $end
$var wire 1 @ b $end
$var wire 1 A c $end
$var wire 1 D a $end
$upscope $end
$scope module and3 $end
$var wire 1 @ b $end
$var wire 1 ? c $end
$var wire 1 C a $end
$upscope $end
$scope module or1 $end
$var wire 1 E b $end
$var wire 1 D c $end
$var wire 1 C d $end
$var wire 1 B a $end
$upscope $end
$scope module xor1 $end
$var wire 1 @ b $end
$var wire 1 ? c $end
$var wire 1 G a $end
$upscope $end
$scope module xor2 $end
$var wire 1 A b $end
$var wire 1 G c $end
$var wire 1 F a $end
$upscope $end
$upscope $end
$scope module sum2 $end
$var wire 1 J a $end
$var wire 1 K b $end
$var wire 1 L ci $end
$var wire 1 M s6 $end
$var wire 1 N s5 $end
$var wire 1 O s4 $end
$var wire 1 P s3 $end
$var wire 1 Q s2 $end
$var wire 1 R s1 $end
$var reg 1 S co $end
$var reg 1 T s $end
$scope module and1 $end
$var wire 1 J b $end
$var wire 1 L c $end
$var wire 1 P a $end
$upscope $end
$scope module and2 $end
$var wire 1 K b $end
$var wire 1 L c $end
$var wire 1 O a $end
$upscope $end
$scope module and3 $end
$var wire 1 K b $end
$var wire 1 J c $end
$var wire 1 N a $end
$upscope $end
$scope module or1 $end
$var wire 1 P b $end
$var wire 1 O c $end
$var wire 1 N d $end
$var wire 1 M a $end
$upscope $end
$scope module xor1 $end
$var wire 1 K b $end
$var wire 1 J c $end
$var wire 1 R a $end
$upscope $end
$scope module xor2 $end
$var wire 1 L b $end
$var wire 1 R c $end
$var wire 1 Q a $end
$upscope $end
$upscope $end
$scope module sum3 $end
$var wire 1 U a $end
$var wire 1 V b $end
$var wire 1 W ci $end
$var wire 1 X s6 $end
$var wire 1 Y s5 $end
$var wire 1 Z s4 $end
$var wire 1 [ s3 $end
$var wire 1 \ s2 $end
$var wire 1 ] s1 $end
$var reg 1 ^ co $end
$var reg 1 _ s $end
$scope module and1 $end
$var wire 1 U b $end
$var wire 1 W c $end
$var wire 1 [ a $end
$upscope $end
$scope module and2 $end
$var wire 1 V b $end
$var wire 1 W c $end
$var wire 1 Z a $end
$upscope $end
$scope module and3 $end
$var wire 1 V b $end
$var wire 1 U c $end
$var wire 1 Y a $end
$upscope $end
$scope module or1 $end
$var wire 1 [ b $end
$var wire 1 Z c $end
$var wire 1 Y d $end
$var wire 1 X a $end
$upscope $end
$scope module xor1 $end
$var wire 1 V b $end
$var wire 1 U c $end
$var wire 1 ] a $end
$upscope $end
$scope module xor2 $end
$var wire 1 W b $end
$var wire 1 ] c $end
$var wire 1 \ a $end
$upscope $end
$upscope $end
$scope module sum4 $end
$var wire 1 ` a $end
$var wire 1 a b $end
$var wire 1 b ci $end
$var wire 1 c s6 $end
$var wire 1 d s5 $end
$var wire 1 e s4 $end
$var wire 1 f s3 $end
$var wire 1 g s2 $end
$var wire 1 h s1 $end
$var reg 1 i co $end
$var reg 1 j s $end
$scope module and1 $end
$var wire 1 ` b $end
$var wire 1 b c $end
$var wire 1 f a $end
$upscope $end
$scope module and2 $end
$var wire 1 a b $end
$var wire 1 b c $end
$var wire 1 e a $end
$upscope $end
$scope module and3 $end
$var wire 1 a b $end
$var wire 1 ` c $end
$var wire 1 d a $end
$upscope $end
$scope module or1 $end
$var wire 1 f b $end
$var wire 1 e c $end
$var wire 1 d d $end
$var wire 1 c a $end
$upscope $end
$scope module xor1 $end
$var wire 1 a b $end
$var wire 1 ` c $end
$var wire 1 h a $end
$upscope $end
$scope module xor2 $end
$var wire 1 b b $end
$var wire 1 h c $end
$var wire 1 g a $end
$upscope $end
$upscope $end
$scope module sum5 $end
$var wire 1 k a $end
$var wire 1 l b $end
$var wire 1 m ci $end
$var wire 1 n s6 $end
$var wire 1 o s5 $end
$var wire 1 p s4 $end
$var wire 1 q s3 $end
$var wire 1 r s2 $end
$var wire 1 s s1 $end
$var reg 1 t co $end
$var reg 1 u s $end
$scope module and1 $end
$var wire 1 k b $end
$var wire 1 m c $end
$var wire 1 q a $end
$upscope $end
$scope module and2 $end
$var wire 1 l b $end
$var wire 1 m c $end
$var wire 1 p a $end
$upscope $end
$scope module and3 $end
$var wire 1 l b $end
$var wire 1 k c $end
$var wire 1 o a $end
$upscope $end
$scope module or1 $end
$var wire 1 q b $end
$var wire 1 p c $end
$var wire 1 o d $end
$var wire 1 n a $end
$upscope $end
$scope module xor1 $end
$var wire 1 l b $end
$var wire 1 k c $end
$var wire 1 s a $end
$upscope $end
$scope module xor2 $end
$var wire 1 m b $end
$var wire 1 s c $end
$var wire 1 r a $end
$upscope $end
$upscope $end
$scope module sum6 $end
$var wire 1 v a $end
$var wire 1 w b $end
$var wire 1 x ci $end
$var wire 1 y s6 $end
$var wire 1 z s5 $end
$var wire 1 { s4 $end
$var wire 1 | s3 $end
$var wire 1 } s2 $end
$var wire 1 ~ s1 $end
$var reg 1 !" co $end
$var reg 1 "" s $end
$scope module and1 $end
$var wire 1 v b $end
$var wire 1 x c $end
$var wire 1 | a $end
$upscope $end
$scope module and2 $end
$var wire 1 w b $end
$var wire 1 x c $end
$var wire 1 { a $end
$upscope $end
$scope module and3 $end
$var wire 1 w b $end
$var wire 1 v c $end
$var wire 1 z a $end
$upscope $end
$scope module or1 $end
$var wire 1 | b $end
$var wire 1 { c $end
$var wire 1 z d $end
$var wire 1 y a $end
$upscope $end
$scope module xor1 $end
$var wire 1 w b $end
$var wire 1 v c $end
$var wire 1 ~ a $end
$upscope $end
$scope module xor2 $end
$var wire 1 x b $end
$var wire 1 ~ c $end
$var wire 1 } a $end
$upscope $end
$upscope $end
$scope module sum7 $end
$var wire 1 #" a $end
$var wire 1 $" b $end
$var wire 1 %" ci $end
$var wire 1 &" s6 $end
$var wire 1 '" s5 $end
$var wire 1 (" s4 $end
$var wire 1 )" s3 $end
$var wire 1 *" s2 $end
$var wire 1 +" s1 $end
$var reg 1 ," co $end
$var reg 1 -" s $end
$scope module and1 $end
$var wire 1 #" b $end
$var wire 1 %" c $end
$var wire 1 )" a $end
$upscope $end
$scope module and2 $end
$var wire 1 $" b $end
$var wire 1 %" c $end
$var wire 1 (" a $end
$upscope $end
$scope module and3 $end
$var wire 1 $" b $end
$var wire 1 #" c $end
$var wire 1 '" a $end
$upscope $end
$scope module or1 $end
$var wire 1 )" b $end
$var wire 1 (" c $end
$var wire 1 '" d $end
$var wire 1 &" a $end
$upscope $end
$scope module xor1 $end
$var wire 1 $" b $end
$var wire 1 #" c $end
$var wire 1 +" a $end
$upscope $end
$scope module xor2 $end
$var wire 1 %" b $end
$var wire 1 +" c $end
$var wire 1 *" a $end
$upscope $end
$upscope $end
$upscope $end
$upscope $end
$scope module and3_p $end
$var wire 1 ." b $end
$var wire 1 /" c $end
$var wire 1 0" d $end
$var wire 1 1" a $end
$upscope $end
$scope module and4_p $end
$var wire 1 2" b $end
$var wire 1 3" c $end
$var wire 1 4" d $end
$var wire 1 5" e $end
$var wire 1 6" a $end
$upscope $end
$scope module and5_p $end
$var wire 1 7" b $end
$var wire 1 8" c $end
$var wire 1 9" d $end
$var wire 1 :" e $end
$var wire 1 ;" f $end
$var wire 1 <" a $end
$upscope $end
$scope module inv_p $end
$var wire 1 =" a $end
$var wire 1 >" b $end
$upscope $end
$scope module or2_p $end
$var wire 1 ?" b $end
$var wire 1 @" c $end
$var wire 1 A" a $end
$upscope $end
$scope module or4_p $end
$var wire 1 B" b $end
$var wire 1 C" c $end
$var wire 1 D" d $end
$var wire 1 E" e $end
$var wire 1 F" a $end
$upscope $end
$scope module or5_p $end
$var wire 1 G" b $end
$var wire 1 H" c $end
$var wire 1 I" d $end
$var wire 1 J" e $end
$var wire 1 K" f $end
$var wire 1 L" a $end
$upscope $end
$scope module xor3_p $end
$var wire 1 M" b $end
$var wire 1 N" c $end
$var wire 1 O" d $end
$var wire 1 P" a $end
$upscope $end
$enddefinitions $end
#0
$dumpvars
xP"
zO"
zN"
zM"
xL"
zK"
zJ"
zI"
zH"
zG"
xF"
zE"
zD"
zC"
zB"
xA"
z@"
z?"
z>"
x="
x<"
z;"
z:"
z9"
z8"
z7"
x6"
z5"
z4"
z3"
z2"
x1"
z0"
z/"
z."
x-"
x,"
x+"
x*"
x)"
x("
x'"
x&"
x%"
x$"
x#"
x""
x!"
x~
x}
x|
x{
xz
xy
xx
xw
xv
xu
xt
xs
xr
xq
xp
xo
xn
xm
xl
xk
xj
xi
xh
xg
xf
xe
xd
xc
xb
xa
x`
x_
x^
x]
x\
x[
xZ
xY
xX
xW
xV
xU
xT
xS
xR
xQ
xP
xO
xN
xM
xL
xK
xJ
xI
xH
xG
xF
xE
xD
xC
xB
xA
x@
x?
x>
x=
x<
x;
x:
x9
x8
x7
x6
x5
bx 4
bx 3
bx 2
01
bx 0
bx /
bx .
bx -
bx ,
bx +
bx *
bx )
bx (
x'
bx &
bx %
x$
bx #
bz "
bz !
$end
#1000
b0 #
b0 -
b0 (
b0 .
b0 +
b0 &
0'
#2000
b1 (
b1 .
0:
09
#3000
b10 (
b10 .
#4000
b1010 ,
b11 (
b11 .
#54000
06
1@
1K
0V
1a
1l
0w
0$"
05
0?
0J
0U
0`
0k
0v
0#"
b110110 *
b110110 0
b0 )
b0 /
b11011011101011010101101101000 ,
b1 +
#56000
0<
1G
1R
0Z
0]
1h
1s
0{
0~
0("
0+"
08
0E
0C
0P
0N
0[
0Y
0f
0d
0q
0o
0|
0z
0)"
0'"
#58000
bx0 %
bx0 4
bx0 2
0>
0;
#59000
0b
0%"
0A
0$
0^
0!"
0,"
b0xx0xx0 3
0=
0X
0y
0&"
07
#61000
b0xx1xx10 %
b0xx1xx10 4
1j
0-"
b0xx1xx10 2
1I
0e
1g
0*"
0D
1F
#64000
0m
0L
0i
b0x00x00 3
0H
0c
0B
#66000
b0x11x110 %
b0x11x110 4
1u
b0x11x110 2
1T
0p
1r
0O
1Q
#69000
0x
0W
0t
b0 3
0S
0n
0M
#71000
b110110 %
b110110 4
0""
b110110 2
0_
0}
0\
#104000
15
1J
1U
1`
1v
1#"
0@
0a
0l
1w
b11011101 )
b11011101 /
b1000100 *
b1000100 0
b11101110100110110111000101110110 ,
b10 +
#106000
1<
1N
0R
1]
1z
1+"
0G
0s
#108000
b10011001 %
b10011001 4
1>
0T
1_
1-"
0I
b10011001 2
0u
1;
0Q
1\
1*"
0F
0r
#109000
1W
1%"
1S
b1000100 3
1!"
1M
1y
#111000
b10001 %
b10001 4
0_
b10001 2
0-"
1[
0\
1)"
0*"
#114000
1b
1$
1^
b11001100 3
1,"
1X
1&"
#116000
b1 %
b1 4
b1 2
0j
1f
0g
#119000
1m
b11011100 3
1i
1c
#121000
b100001 %
b100001 4
b100001 2
1u
1r
#154000
1?
0J
0`
0v
16
0K
1a
1$"
b10001011 )
b10001011 /
b11010001 *
b11010001 0
b11000101110000101001110110110100 ,
b11 +
#156000
1G
0f
0z
1~
18
0<
0N
1e
1("
1'"
0+"
#158000
b11100010 %
b11100010 4
1I
1""
0>
b11100010 2
1-"
1F
1}
0;
1*"
#159000
0%"
1A
0W
0!"
1=
b10011001 3
0S
0y
17
0M
#161000
b1101000 %
b1101000 4
0-"
0I
b1101000 2
1_
0)"
0("
0*"
1E
0F
0[
1\
#164000
1L
0b
1H
b10010011 3
0^
1B
0X
#166000
b1111100 %
b1111100 4
1T
b1111100 2
1j
1Q
0e
1g
#169000
0m
b10000011 3
0i
0c
#171000
b1011100 %
b1011100 4
b1011100 2
0u
0r
#204000
0?
1J
1V
1l
0w
b10001101 )
b10001101 /
b10111001 *
b10111001 0
b1000110101111010100011110100010 ,
b100 +
#206000
0E
0G
1P
1R
1Y
0]
1s
0~
#208000
b110010 %
b110010 4
1I
0T
0_
1u
b110010 2
0""
1F
0Q
0\
1r
0}
#209000
0L
1W
1b
0H
1S
b10001101 3
1^
0B
1M
1X
#211000
b101110 %
b101110 4
1T
1_
b101110 2
0j
0P
1Q
1[
1Z
1\
1e
0g
#214000
0W
1m
0S
b10011001 3
1i
0M
1c
#216000
b110 %
b110 4
0_
b110 2
0u
0[
0Z
0\
1p
0r
#219000
1x
b10111001 3
1t
1n
#221000
b1000110 %
b1000110 4
b1000110 2
1""
1}
#254000
05
1?
0U
1`
1v
1@
0V
0l
0$"
b11010110 )
b11010110 /
b10011 *
b10011 0
b11101011000001100011001011000000 ,
b101 +
#256000
08
1<
1E
1C
1f
1d
0h
1|
1~
1D
0Y
0p
0s
0'"
1+"
#258000
b10110111 %
b10110111 4
1>
1j
0""
1u
b10110111 2
1-"
1;
1g
0}
1r
1*"
#259000
0A
1%"
1L
0b
0x
0$
0=
1!"
1H
0^
0t
b1010010 3
0,"
07
1y
1B
0X
0n
0&"
#261000
b1100001 %
b1100001 4
0I
0-"
0T
0j
b1100001 2
1""
0E
0D
0F
1)"
0*"
1P
0Q
0f
0e
0g
0|
1}
#264000
1W
0%"
1$
1,"
1S
b10010110 3
0!"
1&"
1M
0y
#266000
b11101001 %
b11101001 4
1_
b11101001 2
1-"
1\
0)"
1*"
#269000
0$
b10110 3
0,"
0&"
#304000
0J
0`
1k
06
1K
1V
0a
1l
1w
b11100010 )
b11100010 /
b1101110 *
b1101110 0
b11110001011000111010111010001110 ,
b110 +
#306000
0P
1q
1o
0<
1O
1Z
1]
0d
1p
1z
0~
#308000
b10100000 %
b10100000 4
0>
0_
b10100000 2
0""
0;
0\
0}
#309000
1b
0m
1x
1%"
1^
0i
1t
b1101110 3
1!"
1X
0c
1n
1y
#311000
b1010000 %
b1010000 4
1j
0u
1""
b1010000 2
0-"
1g
0q
0p
0r
1|
1{
1}
1)"
0*"
#314000
1$
b11101110 3
1,"
1&"
#354000
0?
1U
0k
0#"
0V
1a
0l
0w
b1001000 )
b1001000 /
b10110 *
b10110 0
b100100001111010111011010001100 ,
b111 +
#356000
0C
1G
1[
0)"
0+"
0Z
1e
1h
0o
0{
0z
1~
#358000
b10000010 %
b10000010 4
1I
1-"
0j
b10000010 2
0""
1F
1*"
0g
0}
#359000
0L
1m
0x
0$
0H
0,"
1i
b1011100 3
0t
0B
0&"
1c
0n
#361000
b11100110 %
b11100110 4
1T
1u
b11100110 2
1""
0O
1Q
1r
0|
1}
#364000
0W
0%"
0S
b11000 3
0!"
0M
0y
#366000
b1101110 %
b1101110 4
1_
b1101110 2
0-"
0[
1\
0*"
#369000
0b
b10000 3
0^
0X
#371000
b1111110 %
b1111110 4
b1111110 2
1j
0e
1g
#374000
0m
b0 3
0i
0c
#376000
b1011110 %
b1011110 4
b1011110 2
0u
0r
#404000
15
1J
0U
1k
16
0@
1l
b1100101 )
b1100101 /
b110101 *
b110101 0
b110010100111011001001000111010 ,
b1000 +
#406000
18
1N
0R
0]
1o
0G
#408000
b1010000 %
b1010000 4
0T
0_
b1010000 2
0I
0Q
0\
0F
#409000
1A
1W
1x
1=
1S
b100101 3
1t
17
1M
1n
#411000
b11010 %
b11010 4
1I
1_
b11010 2
0""
1F
1\
1|
0}
#414000
1%"
b1100101 3
1!"
1y
#416000
b10011010 %
b10011010 4
b10011010 2
1-"
1*"
#454000
0J
1`
0v
1#"
b10110001 )
b10110001 /
b1011000100101000011010100011000 ,
b1001 +
#456000
0N
1R
1d
0h
0|
0~
1)"
1+"
#458000
b1001110 %
b1001110 4
1T
0j
1""
b1001110 2
0-"
1Q
0g
1}
0*"
#459000
0W
1m
0%"
1$
0S
1i
0!"
b10110001 3
1,"
0M
1c
0y
1&"
#461000
b11100110 %
b11100110 4
0_
1u
b11100110 2
1-"
0\
1q
1p
1r
0)"
1*"
#464000
0$
b110001 3
0,"
0&"
#504000
05
0`
0k
1v
06
0l
1w
b11000000 )
b11000000 /
b1010100 *
b1010100 0
b1100000011101101001111010100110 ,
b1010 +
#506000
0d
1h
0q
1|
1z
08
0p
0o
1{
#508000
b11110110 %
b11110110 4
b11110110 2
1j
1g
#509000
0m
0x
0A
1%"
0i
0t
0=
b1000000 3
1!"
0c
0n
07
1y
